pcdp/ALARM.cp38-win32.pyd
pcdp/RDFM.cp38-win32.pyd
pcdp/__init__.py
pcdp/utils.cp38-win32.pyd
pypcdp-0.24.dist-info/METADATA
pypcdp-0.24.dist-info/WHEEL
pypcdp-0.24.dist-info/top_level.txt
pypcdp-0.24.dist-info/RECORD
