Metadata-Version: 2.1
Name: pypcdp
Version: 0.24
Summary: PCDP api
Author: xgzh
Author-email: 
License: UNKNOWN
Platform: UNKNOWN
Classifier: Topic :: Software Development
Classifier: Development Status :: 3 - Alpha
Classifier: License :: OSI Approved :: MIT License
Classifier: Programming Language :: Python :: 3.8
Classifier: Intended Audience :: Developers
Requires-Python: >=3.8
